wellog/__init__.py
wellog/logger.py
wellog-0.0.1.dist-info/LICENSE
wellog-0.0.1.dist-info/METADATA
wellog-0.0.1.dist-info/WHEEL
wellog-0.0.1.dist-info/top_level.txt
wellog-0.0.1.dist-info/RECORD
