Metadata-Version: 2.1
Name: wellog
Version: 0.0.1
Summary: Registros
Home-page: https://gitwell.gwldx.com:2443/python_libraries/manager_logs
Author: Pedro Jesús Pérez Hernández
Author-email: pedrojesus.perez@welldex.mx
License: MIT
License-File: LICENSE
Requires-Dist: loguru
